[
 {
  "name": "Abashiri",
  "position": 440014415
 },
 {
  "name": "AbashiriWan",
  "position": 440014430
 },
 {
  "name": "AbukumaGawa",
  "position": 380614052
 },
 {
  "name": "Abukumasammyaku",
  "position": 373014045
 },
 {
  "name": "Aichi",
  "position": 350013715
 },
 {
  "name": "Aikawa",
  "position": 380213815
 },
 {
  "name": "Aizuwakamatsu",
  "position": 373013956
 },
 {
  "name": "Akabira",
  "position": 433314205
 },
 {
  "name": "Akashi",
  "position": 344513458
 },
 {
  "name": "Aki",
  "position": 333013354
 },
 {
  "name": "Akita",
  "position": 394514007
 },
 {
  "name": "Akita",
  "position": 394014030
 },
 {
  "name": "Akkeshi",
  "position": 430214451
 },
 {
  "name": "Ako",
  "position": 34452130
 },
 {
  "name": "Akusekishima",
  "position": 292712937
 },
 {
  "name": "Amagasaki",
  "position": 344213520
 },
 {
  "name": "Amakusashoto",
  "position": 321513010
 },
 {
  "name": "AmamiGunto",
  "position": 271612921
 },
 {
  "name": "AmamiOshima",
  "position": 280012900
 },
 {
  "name": "Anan",
  "position": 335413440
 },
 {
  "name": "Aogashima",
  "position": 322813946
 },
 {
  "name": "Aomori",
  "position": 404514040
 },
 {
  "name": "Arida",
  "position": 340513508
 },
 {
  "name": "AsahiGawa",
  "position": 343613358
 },
 {
  "name": "Asahigawa",
  "position": 434614222
 },
 {
  "name": "Ashibetsu",
  "position": 433114211
 },
 {
  "name": "Ashikaga",
  "position": 362813929
 },
 {
  "name": "AshizuriZaki",
  "position": 324413300
 },
 {
  "name": "Atami",
  "position": 350513904
 },
 {
  "name": "Atsuta",
  "position": 432414126
 },
 {
  "name": "Awajishima",
  "position": 343013450
 },
 {
  "name": "Ayabe",
  "position": 352013520
 },
 {
  "name": "Bandaisan",
  "position": 373614004
 },
 {
  "name": "Bibai",
  "position": 431914152
 },
 {
  "name": "BiwaKo",
  "position": 351513610
 },
 {
  "name": "Bizen",
  "position": 344313408
 },
 {
  "name": "Bungosuido",
  "position": 330013215
 },
 {
  "name": "Bungotakada",
  "position": 333513125
 },
 {
  "name": "Buzen",
  "position": 333513105
 },
 {
  "name": "Chiba",
  "position": 353014020
 },
 {
  "name": "Chichibu",
  "position": 355913910
 },
 {
  "name": "Chino",
  "position": 355913809
 },
 {
  "name": "Chitose",
  "position": 424914139
 },
 {
  "name": "Chokaisan",
  "position": 390614003
 },
 {
  "name": "Chubu",
  "position": 364513730
 },
 {
  "name": "Chugoku",
  "position": 350013300
 },
 {
  "name": "Chugokusanchi",
  "position": 350013300
 },
 {
  "name": "Daisen",
  "position": 352213332
 },
 {
  "name": "DaioMisaki",
  "position": 341513645
 },
 {
  "name": "DaisetsuZan",
  "position": 433014257
 },
 {
  "name": "betsu",
  "position": 430714134
 },
 {
  "name": "chigosammyaku",
  "position": 365013950
 },
 {
  "name": "chizenMisaki",
  "position": 355913557
 },
 {
  "name": "hime",
  "position": 28003100
 },
 {
  "name": "mbetsu",
  "position": 444414147
 },
 {
  "name": "na",
  "position": 352513725
 },
 {
  "name": "ngaru",
  "position": 440314331
 },
 {
  "name": "rimoMisaki",
  "position": 415014315
 },
 {
  "name": "sanMisaki",
  "position": 414014110
 },
 {
  "name": "sashiHokkaido",
  "position": 445614235
 },
 {
  "name": "sashiHokkaido",
  "position": 415214007
 },
 {
  "name": "Fuchu",
  "position": 343413314
 },
 {
  "name": "Fuji",
  "position": 350913839
 },
 {
  "name": "Fujisan",
  "position": 352213844
 },
 {
  "name": "FujiYoshida",
  "position": 353013846
 },
 {
  "name": "Fujinomiya",
  "position": 351013840
 },
 {
  "name": "FujiyamaMtFujisan",
  "position": 352213844
 },
 {
  "name": "Fukuchiyama",
  "position": 351913509
 },
 {
  "name": "Fukueshima",
  "position": 324012845
 },
 {
  "name": "Fukui",
  "position": 360513610
 },
 {
  "name": "Fukui",
  "position": 360013612
 },
 {
  "name": "Fukuoka",
  "position": 333913021
 },
 {
  "name": "Fukuoka",
  "position": 333013100
 },
 {
  "name": "Fukushima",
  "position": 374414028
 },
 {
  "name": "Fukushima",
  "position": 373014015
 },
 {
  "name": "Fukuyama",
  "position": 343513320
 },
 {
  "name": "Funabashi",
  "position": 354514000
 },
 {
  "name": "Furano",
  "position": 432114223
 },
 {
  "name": "Furukawa",
  "position": 383414058
 },
 {
  "name": "Gamagori",
  "position": 345013714
 },
 {
  "name": "Gassan",
  "position": 383214001
 },
 {
  "name": "Gero",
  "position": 354813714
 },
 {
  "name": "Gifu",
  "position": 354013700
 },
 {
  "name": "Gonoura",
  "position": 334412940
 },
 {
  "name": "Gobo",
  "position": 335313510
 },
 {
  "name": "Gojo",
  "position": 342113542
 },
 {
  "name": "Goshogawara",
  "position": 404814027
 },
 {
  "name": "GotoRetto",
  "position": 325512905
 },
 {
  "name": "Gotsu",
  "position": 350013214
 },
 {
  "name": "Gumma",
  "position": 363013820
 },
 {
  "name": "Haboro",
  "position": 442214142
 },
 {
  "name": "HachijoJima",
  "position": 330513945
 },
 {
  "name": "Hachinohe",
  "position": 403014129
 },
 {
  "name": "Hachioji",
  "position": 354013920
 },
 {
  "name": "HakkenZen",
  "position": 341013554
 },
 {
  "name": "Hakusan",
  "position": 360913646
 },
 {
  "name": "Hakui",
  "position": 365313647
 },
 {
  "name": "Hamada",
  "position": 345613204
 },
 {
  "name": "Hamamatsu",
  "position": 344513745
 },
 {
  "name": "Hanamaki",
  "position": 392314107
 },
 {
  "name": "Handa",
  "position": 345313655
 },
 {
  "name": "Haranomachi",
  "position": 373814058
 },
 {
  "name": "Hashimoto",
  "position": 341913537
 },
 {
  "name": "Haterumashima",
  "position": 240312347
 },
 {
  "name": "Hayachinesan",
  "position": 393414129
 },
 {
  "name": "HenashiMisaki",
  "position": 403713951
 },
 {
  "name": "HidaGawa",
  "position": 352613703
 },
 {
  "name": "Hidasammyaku",
  "position": 363013740
 },
 {
  "name": "Hidakasammyaku",
  "position": 423514245
 },
 {
  "name": "Higashiajimasan",
  "position": 374014010
 },
 {
  "name": "Higashiosaka",
  "position": 344013537
 },
 {
  "name": "Hikari",
  "position": 335813158
 },
 {
  "name": "Hikone",
  "position": 351513610
 },
 {
  "name": "Himeji",
  "position": 345013440
 },
 {
  "name": "Himi",
  "position": 365013655
 },
 {
  "name": "Hirado",
  "position": 332212933
 },
 {
  "name": "Hiratsuka",
  "position": 351913921
 },
 {
  "name": "Hiroo",
  "position": 421714319
 },
 {
  "name": "Hirosaki",
  "position": 403414028
 },
 {
  "name": "Hiroshima",
  "position": 345013300
 },
 {
  "name": "Hita",
  "position": 332013058
 },
 {
  "name": "Hitachi",
  "position": 363614039
 },
 {
  "name": "Hitoyoshi",
  "position": 321313045
 },
 {
  "name": "HodakaDake",
  "position": 361713739
 },
 {
  "name": "Hofu",
  "position": 340313134
 },
 {
  "name": "Hojo",
  "position": 335813246
 },
 {
  "name": "Hokkaido",
  "position": 433014300
 },
 {
  "name": "Honbetsu",
  "position": 430714337
 },
 {
  "name": "Hondo",
  "position": 322713012
 },
 {
  "name": "Honjo",
  "position": 392314003
 },
 {
  "name": "Honshu",
  "position": 360013800
 },
 {
  "name": "Horobetsu",
  "position": 422414106
 },
 {
  "name": "Hyogo",
  "position": 351513450
 },
 {
  "name": "Hyuga",
  "position": 322513135
 },
 {
  "name": "Ibaraki",
  "position": 361014010
 },
 {
  "name": "Ibusuki",
  "position": 311213040
 },
 {
  "name": "Ichihara",
  "position": 352814005
 },
 {
  "name": "Ichikawa",
  "position": 354413955
 },
 {
  "name": "Ichinohe",
  "position": 401314117
 },
 {
  "name": "Ichinomiya",
  "position": 351813648
 },
 {
  "name": "Ichinoseki",
  "position": 385514108
 },
 {
  "name": "Iheyashima",
  "position": 270412758
 },
 {
  "name": "Iishima",
  "position": 264312747
 },
 {
  "name": "Iida",
  "position": 353513750
 },
 {
  "name": "Iiyama",
  "position": 365113822
 },
 {
  "name": "Iizuka",
  "position": 333813042
 },
 {
  "name": "Ikeda",
  "position": 340113348
 },
 {
  "name": "Iki",
  "position": 334512942
 },
 {
  "name": "Imabari",
  "position": 340413300
 },
 {
  "name": "Imari",
  "position": 331512952
 },
 {
  "name": "Ina",
  "position": 355013755
 },
 {
  "name": "InawashiroKo",
  "position": 372914006
 },
 {
  "name": "InlandSeaSetonaikai",
  "position": 342013330
 },
 {
  "name": "Innoshima",
  "position": 341913310
 },
 {
  "name": "IoJima",
  "position": 304813018
 },
 {
  "name": "IrabuJima",
  "position": 245012510
 },
 {
  "name": "IriomoteJima",
  "position": 241912348
 },
 {
  "name": "IroZaki",
  "position": 343613851
 },
 {
  "name": "Isahaya",
  "position": 325213002
 },
 {
  "name": "IseWan",
  "position": 344313643
 },
 {
  "name": "Ishigakishima",
  "position": 242012410
 },
 {
  "name": "IshikariGawa",
  "position": 431514123
 },
 {
  "name": "Ishikarisammyaku",
  "position": 433014300
 },
 {
  "name": "IshikariWan",
  "position": 432514101
 },
 {
  "name": "Ishikawa",
  "position": 363013630
 },
 {
  "name": "Ishinomaki",
  "position": 383214120
 },
 {
  "name": "Ishioka",
  "position": 361114016
 },
 {
  "name": "Ito",
  "position": 345813905
 },
 {
  "name": "Itoigawa",
  "position": 370213751
 },
 {
  "name": "Iwaizumi",
  "position": 395014145
 },
 {
  "name": "Iwaki",
  "position": 370314055
 },
 {
  "name": "Iwakuni",
  "position": 341513208
 },
 {
  "name": "Iwamizawa",
  "position": 431214146
 },
 {
  "name": "Iwanai",
  "position": 425814030
 },
 {
  "name": "Iwata",
  "position": 344213751
 },
 {
  "name": "Iwate",
  "position": 393014130
 },
 {
  "name": "Iwatesan",
  "position": 395114100
 },
 {
  "name": "Iyo",
  "position": 334513245
 },
 {
  "name": "Izenashima",
  "position": 265612756
 },
 {
  "name": "Izushoto",
  "position": 343014000
 },
 {
  "name": "Izumisano",
  "position": 342313518
 },
 {
  "name": "Izumo",
  "position": 352013246
 },
 {
  "name": "JizoZaki",
  "position": 353413320
 },
 {
  "name": "Joetsu",
  "position": 371213810
 },
 {
  "name": "Kagawa",
  "position": 341513400
 },
 {
  "name": "Kagoshima",
  "position": 313513033
 },
 {
  "name": "Kagoshima",
  "position": 313013030
 },
 {
  "name": "Kake",
  "position": 343613219
 },
 {
  "name": "Kakegawa",
  "position": 344513801
 },
 {
  "name": "KakeromaJima",
  "position": 280812914
 },
 {
  "name": "Kakogawa",
  "position": 344613451
 },
 {
  "name": "Kamaishi",
  "position": 391614153
 },
 {
  "name": "Kameoka",
  "position": 350013535
 },
 {
  "name": "Kaminoyama",
  "position": 380914017
 },
 {
  "name": "Kamo",
  "position": 373913903
 },
 {
  "name": "KamuiMisaki",
  "position": 432014021
 },
 {
  "name": "Kanonji",
  "position": 340713339
 },
 {
  "name": "Kanoya",
  "position": 312513050
 },
 {
  "name": "Kanto",
  "position": 361513930
 },
 {
  "name": "Kantosanchi",
  "position": 355913850
 },
 {
  "name": "Kanuma",
  "position": 363413942
 },
 {
  "name": "Karasuyama",
  "position": 363914009
 },
 {
  "name": "Karatsu",
  "position": 332612958
 },
 {
  "name": "Kashiwazaki",
  "position": 372213833
 },
 {
  "name": "Kasumi",
  "position": 353813438
 },
 {
  "name": "Katsumoto",
  "position": 335112942
 },
 {
  "name": "Katsuura",
  "position": 351014020
 },
 {
  "name": "Katsuyama",
  "position": 360313630
 },
 {
  "name": "Kawagoe",
  "position": 355513929
 },
 {
  "name": "Kawaguchi",
  "position": 355213945
 },
 {
  "name": "Kawanoe",
  "position": 340113334
 },
 {
  "name": "Kazuno",
  "position": 401014045
 },
 {
  "name": "KeramaRetto",
  "position": 260512715
 },
 {
  "name": "Kesennuma",
  "position": 385414135
 },
 {
  "name": "Kiisanchi",
  "position": 342013600
 },
 {
  "name": "Kiisuido",
  "position": 334013445
 },
 {
  "name": "Kikaigashima",
  "position": 281912959
 },
 {
  "name": "Kinki",
  "position": 334513600
 },
 {
  "name": "Kinomoto",
  "position": 353013613
 },
 {
  "name": "Kiryu",
  "position": 362413920
 },
 {
  "name": "Kisarazu",
  "position": 352313955
 },
 {
  "name": "Kishiwada",
  "position": 342813522
 },
 {
  "name": "KisoGawa",
  "position": 352013645
 },
 {
  "name": "Kisosammyaku",
  "position": 354513745
 },
 {
  "name": "Kisofukushima",
  "position": 355213743
 },
 {
  "name": "Kitaibaraki",
  "position": 365014045
 },
 {
  "name": "Kitakami",
  "position": 392014110
 },
 {
  "name": "KitakamiGawa",
  "position": 382514119
 },
 {
  "name": "Kitakamisammyaku",
  "position": 393014130
 },
 {
  "name": "Kitakata",
  "position": 373913952
 },
 {
  "name": "Kitakyushu",
  "position": 335013050
 },
 {
  "name": "Kitami",
  "position": 434814354
 },
 {
  "name": "Kitamisammyaku",
  "position": 442214243
 },
 {
  "name": "Kitsuki",
  "position": 332513137
 },
 {
  "name": "Kobayashi",
  "position": 315613059
 },
 {
  "name": "Kobisho",
  "position": 255612341
 },
 {
  "name": "Kochi",
  "position": 334013330
 },
 {
  "name": "Kofu",
  "position": 354013830
 },
 {
  "name": "Koga",
  "position": 361113943
 },
 {
  "name": "Kokubu",
  "position": 314413046
 },
 {
  "name": "Komatsushima",
  "position": 340013435
 },
 {
  "name": "Komoro",
  "position": 361913826
 },
 {
  "name": "Konosu",
  "position": 360313931
 },
 {
  "name": "Koriyama",
  "position": 372414023
 },
 {
  "name": "KoshikiRetto",
  "position": 314512949
 },
 {
  "name": "Koza",
  "position": 261912746
 },
 {
  "name": "Kubokawa",
  "position": 331213308
 },
 {
  "name": "KuchinoerubaJima",
  "position": 302813012
 },
 {
  "name": "Kuchinoshima",
  "position": 295712955
 },
 {
  "name": "Kuchinotsu",
  "position": 323613011
 },
 {
  "name": "Kuji",
  "position": 401114146
 },
 {
  "name": "Kujusan",
  "position": 330513115
 },
 {
  "name": "Kumagaya",
  "position": 360913922
 },
 {
  "name": "Kumamoto",
  "position": 325513055
 },
 {
  "name": "Kumeshima",
  "position": 262012647
 },
 {
  "name": "Kurayoshi",
  "position": 352613350
 },
 {
  "name": "Kure",
  "position": 341413232
 },
 {
  "name": "Kurino",
  "position": 315713043
 },
 {
  "name": "KuroshimaKagoshima",
  "position": 305012957
 },
 {
  "name": "KuroshimaOkinawa",
  "position": 241412401
 },
 {
  "name": "Kurume",
  "position": 331513030
 },
 {
  "name": "Kusatsu",
  "position": 363713836
 },
 {
  "name": "Kushikino",
  "position": 314413016
 },
 {
  "name": "Kushima",
  "position": 312913114
 },
 {
  "name": "Kushimoto",
  "position": 332813547
 },
 {
  "name": "Kushiro",
  "position": 430014425
 },
 {
  "name": "KushiroGawa",
  "position": 425914423
 },
 {
  "name": "KussharoKo",
  "position": 433814421
 },
 {
  "name": "Kuwana",
  "position": 350513643
 },
 {
  "name": "Kyogoasaki",
  "position": 354513515
 },
 {
  "name": "Kyoto",
  "position": 350013545
 },
 {
  "name": "Kyoto",
  "position": 351513545
 },
 {
  "name": "Kyushu",
  "position": 330013100
 },
 {
  "name": "Kyushu",
  "position": 330013100
 },
 {
  "name": "Kyushusanchi",
  "position": 323513117
 },
 {
  "name": "Maebashi",
  "position": 362413904
 },
 {
  "name": "Maizuru",
  "position": 352513522
 },
 {
  "name": "Makurazaki",
  "position": 311513020
 },
 {
  "name": "Marugame",
  "position": 341513340
 },
 {
  "name": "Masuda",
  "position": 344013151
 },
 {
  "name": "Matsumae",
  "position": 412614007
 },
 {
  "name": "Matsumoto",
  "position": 36151380
 },
 {
  "name": "MatsuuraN",
  "position": 332012949
 },
 {
  "name": "Maatsuyama",
  "position": 334512345
 },
 {
  "name": "Matto",
  "position": 363113634
 },
 {
  "name": "MebechiGawa",
  "position": 403114131
 },
 {
  "name": "Mie",
  "position": 343013610
 },
 {
  "name": "Mihara",
  "position": 342413305
 },
 {
  "name": "mine",
  "position": 341213107
 },
 {
  "name": "Mino",
  "position": 3533213655
 },
 {
  "name": "Misawa",
  "position": 404114124
 },
 {
  "name": "Mishima",
  "position": 351013852
 },
 {
  "name": "Mito",
  "position": 362014030
 },
 {
  "name": "Mitsukaido",
  "position": 360113959
 },
 {
  "name": "Miyagi",
  "position": 381514045
 },
 {
  "name": "MiyakeJimla",
  "position": 340513930
 },
 {
  "name": "MiyakoRetto",
  "position": 24241250
 },
 {
  "name": "Miyakonojo",
  "position": 314013105
 },
 {
  "name": "MiyanouraDake",
  "position": 302013031
 },
 {
  "name": "Mihyazaki",
  "position": 323013130
 },
 {
  "name": "Miyazu",
  "position": 353513510
 },
 {
  "name": "Miyoshi",
  "position": 344813251
 },
 {
  "name": "Mizusawa",
  "position": 390814108
 },
 {
  "name": "MogamiGawa",
  "position": 38451400
 },
 {
  "name": "Mombetsu",
  "position": 442114322
 },
 {
  "name": "Morioka",
  "position": 394514108
 },
 {
  "name": "Mugi",
  "position": 334013425
 },
 {
  "name": "Murakami",
  "position": 381413929
 },
 {
  "name": "Murayama",
  "position": 383014025
 },
 {
  "name": "Muroran",
  "position": 42251410
 },
 {
  "name": "Muroto",
  "position": 331813409
 },
 {
  "name": "MurotoMisaki",
  "position": 331513410
 },
 {
  "name": "MutsuWan",
  "position": 410514055
 },
 {
  "name": "Nabari",
  "position": 343713605
 },
 {
  "name": "Nagahama",
  "position": 352313616
 },
 {
  "name": "Nagai",
  "position": 380614002
 },
 {
  "name": "Nagano",
  "position": 36413810
 },
 {
  "name": "Nagano",
  "position": 36421380
 },
 {
  "name": "Nagoka",
  "position": 372713851
 },
 {
  "name": "Nagasaki",
  "position": 324712950
 },
 {
  "name": "Nagasaki",
  "position": 325012940
 },
 {
  "name": "Nagato",
  "position": 341913105
 },
 {
  "name": "Naha",
  "position": 261312742
 },
 {
  "name": "Nakadorishima",
  "position": 325712904
 },
 {
  "name": "Nakaminato",
  "position": 362114036
 },
 {
  "name": "Nakamura",
  "position": 325913256
 },
 {
  "name": "Nakano",
  "position": 364513822
 },
 {
  "name": "nakanoshima",
  "position": 295112952
 },
 {
  "name": "Nakashibetsu",
  "position": 433314459
 },
 {
  "name": "Nandan",
  "position": 341013442
 },
 {
  "name": "Nankoku",
  "position": 333913344
 },
 {
  "name": "Nara",
  "position": 34301360
 },
 {
  "name": "Naruto",
  "position": 341113437
 },
 {
  "name": "Nayoro",
  "position": 442114228
 },
 {
  "name": "Nemuro",
  "position": 432014535
 },
 {
  "name": "NemuroKaikyo",
  "position": 433014530
 },
 {
  "name": "Nichinan",
  "position": 313813123
 },
 {
  "name": "NiiJima",
  "position": 342013915
 },
 {
  "name": "Niigata",
  "position": 371513845
 },
 {
  "name": "Niihama",
  "position": 335513316
 },
 {
  "name": "Niimi",
  "position": 345913328
 },
 {
  "name": "Niitsu",
  "position": 374813907
 },
 {
  "name": "Nikko",
  "position": 364513935
 },
 {
  "name": "Nirasaki",
  "position": 354213827
 },
 {
  "name": "Nishinomiya",
  "position": 344513520
 },
 {
  "name": "Nishinoomote",
  "position": 304313059
 },
 {
  "name": "Nishiwaki",
  "position": 345913458
 },
 {
  "name": "Nobeoka",
  "position": 323613141
 },
 {
  "name": "Noda",
  "position": 355613952
 },
 {
  "name": "Nogata",
  "position": 334813044
 },
 {
  "name": "NojimaZaki",
  "position": 345413953
 },
 {
  "name": "NomiZaki",
  "position": 323512944
 },
 {
  "name": "Noshiro",
  "position": 40121400
 },
 {
  "name": "Numata",
  "position": 364513904
 },
 {
  "name": "Nunazu",
  "position": 350713851
 },
 {
  "name": "Oshima",
  "position": 344413924
 },
 {
  "name": "OakanDake",
  "position": 432714410
 },
 {
  "name": "Obama",
  "position": 353013545
 },
 {
  "name": "Obihiro",
  "position": 425614312
 },
 {
  "name": "Oda",
  "position": 351113230
 },
 {
  "name": "Odate",
  "position": 401614034
 },
 {
  "name": "Odawara",
  "position": 352013906
 },
 {
  "name": "Ofunato",
  "position": 390414143
 },
 {
  "name": "Oga",
  "position": 395513950
 },
 {
  "name": "OgaHanto",
  "position": 395813947
 },
 {
  "name": "Ogaki",
  "position": 352113637
 },
 {
  "name": "Ohata",
  "position": 412414110
 },
 {
  "name": "Oita",
  "position": 331413136
 },
 {
  "name": "Ojiya",
  "position": 371813848
 },
 {
  "name": "Okaya",
  "position": 360513810
 },
 {
  "name": "Okayama",
  "position": 35013350
 },
 {
  "name": "Okazaki",
  "position": 345713710
 },
 {
  "name": "Okishoto",
  "position": 360513315
 },
 {
  "name": "Okinawa",
  "position": 26401280
 },
 {
  "name": "OkinawaGunto",
  "position": 26401280
 },
 {
  "name": "OkinawaJima",
  "position": 26321280
 },
 {
  "name": "Okinoerabushima",
  "position": 272112833
 },
 {
  "name": "OkushiriTo",
  "position": 421513930
 },
 {
  "name": "Oma",
  "position": 414514105
 },
 {
  "name": "Omachi",
  "position": 363013750
 },
 {
  "name": "OmaeZaki",
  "position": 343613814
 },
 {
  "name": "Omagari",
  "position": 392714029
 },
 {
  "name": "Ominato",
  "position": 411714110
 },
 {
  "name": "Omiya",
  "position": 355413938
 },
 {
  "name": "OmonoGawa",
  "position": 394614003
 },
 {
  "name": "Omu",
  "position": 443414258
 },
 {
  "name": "Omura",
  "position": 325612957
 },
 {
  "name": "Omuta",
  "position": 330513026
 },
 {
  "name": "Onoda",
  "position": 335913111
 },
 {
  "name": "Ontakesan",
  "position": 355313729
 },
 {
  "name": "OsumiKaikyo",
  "position": 30551310
 },
 {
  "name": "Osumishoto",
  "position": 30301300
 },
 {
  "name": "Otake",
  "position": 341213213
 },
 {
  "name": "Otaru",
  "position": 43101410
 },
 {
  "name": "OtaruWanIshikariWan",
  "position": 432514101
 },
 {
  "name": "Otoineppu",
  "position": 444414216
 },
 {
  "name": "Otsuki",
  "position": 353613857
 },
 {
  "name": "Ousammyaku",
  "position": 392014035
 },
 {
  "name": "Owase",
  "position": 340713612
 },
 {
  "name": "Oyama",
  "position": 361813948
 },
 {
  "name": "Oyubari",
  "position": 430114205
 },
 {
  "name": "PoroshiriDake",
  "position": 424114252
 },
 {
  "name": "RausuDake",
  "position": 440414507
 },
 {
  "name": "RebunTo",
  "position": 452314102
 },
 {
  "name": "RishiriTo",
  "position": 451114115
 },
 {
  "name": "Rumoi",
  "position": 435614139
 },
 {
  "name": "Sado",
  "position": 38013825
 },
 {
  "name": "Sagae",
  "position": 382214017
 },
 {
  "name": "Saijo",
  "position": 335513311
 },
 {
  "name": "Saiki",
  "position": 325813151
 },
 {
  "name": "Saiki",
  "position": 325813151
 },
 {
  "name": "Sakai",
  "position": 343013530
 },
 {
  "name": "Sakaide",
  "position": 341913350
 },
 {
  "name": "Sakaiminato",
  "position": 353813311
 },
 {
  "name": "SakashimaGunto",
  "position": 24461240
 },
 {
  "name": "Sakata",
  "position": 385513950
 },
 {
  "name": "Sakuma",
  "position": 35313749
 },
 {
  "name": "Sakurai",
  "position": 343013551
 },
 {
  "name": "Samani",
  "position": 42714256
 },
 {
  "name": "Sanda",
  "position": 345313514
 },
 {
  "name": "Sanjo",
  "position": 373713857
 },
 {
  "name": "Sapporo",
  "position": 43014121
 },
 {
  "name": "SataMisaki",
  "position": 31013040
 },
 {
  "name": "Sawara",
  "position": 355514030
 },
 {
  "name": "SendaiKagoshima",
  "position": 315013020
 },
 {
  "name": "SendaiMiyagi",
  "position": 381514053
 },
 {
  "name": "SendaiWan",
  "position": 38151410
 },
 {
  "name": "Setana",
  "position": 422613951
 },
 {
  "name": "Setonaikai",
  "position": 342013330
 },
 {
  "name": "SikotuKo",
  "position": 424514125
 },
 {
  "name": "SofuGan",
  "position": 294914021
 },
 {
  "name": "Soma",
  "position": 374014050
 },
 {
  "name": "SoyaMisaki",
  "position": 453014155
 },
 {
  "name": "Susaki",
  "position": 332213317
 },
 {
  "name": "Suttsu",
  "position": 424814014
 },
 {
  "name": "SuwanoseJima",
  "position": 293812943
 },
 {
  "name": "Suzu",
  "position": 37251717
 },
 {
  "name": "Suzuka",
  "position": 345513636
 },
 {
  "name": "Takada",
  "position": 37713815
 },
 {
  "name": "Takaoka",
  "position": 36471370
 },
 {
  "name": "Takefu",
  "position": 355013610
 },
 {
  "name": "Taketa",
  "position": 325813124
 },
 {
  "name": "Takeo",
  "position": 33121301
 },
 {
  "name": "Taketa",
  "position": 325813124
 },
 {
  "name": "Tamano",
  "position": 342913359
 },
 {
  "name": "Tamashima",
  "position": 343213340
 },
 {
  "name": "Tanabe",
  "position": 334413522
 },
 {
  "name": "TaramaJima",
  "position": 243912442
 },
 {
  "name": "Tateyama",
  "position": 35013950
 },
 {
  "name": "Tatsuno",
  "position": 345213433
 },
 {
  "name": "Teshio",
  "position": 445314144
 },
 {
  "name": "Toba",
  "position": 343013651
 },
 {
  "name": "Tochigi",
  "position": 362513945
 },
 {
  "name": "Tochigi",
  "position": 364513945
 },
 {
  "name": "Tohoku",
  "position": 395014145
 },
 {
  "name": "TokachiDake",
  "position": 431741425
 },
 {
  "name": "Tokamachi",
  "position": 37813843
 },
 {
  "name": "TokaraRetto",
  "position": 293712943
 },
 {
  "name": "TokashikiShima",
  "position": 261112721
 },
 {
  "name": "TokachiGawa",
  "position": 424414342
 },
 {
  "name": "Tokamachi",
  "position": 37813843
 },
 {
  "name": "TokunoShima",
  "position": 275612855
 },
 {
  "name": "Tokuyama",
  "position": 34313150
 },
 {
  "name": "Tomakomai",
  "position": 423814136
 },
 {
  "name": "ToneGawa",
  "position": 354414051
 },
 {
  "name": "Tono",
  "position": 391914132
 },
 {
  "name": "Tosa",
  "position": 332413323
 },
 {
  "name": "TosaShimizu",
  "position": 325213258
 },
 {
  "name": "Tosu",
  "position": 332213031
 },
 {
  "name": "Tottori",
  "position": 353013415
 },
 {
  "name": "Tottori",
  "position": 353013412
 },
 {
  "name": "Towada",
  "position": 403714113
 },
 {
  "name": "Toyako",
  "position": 423514051
 },
 {
  "name": "Tsu",
  "position": 344513625
 },
 {
  "name": "Tsuchiura",
  "position": 36514015
 },
 {
  "name": "Tsuruga",
  "position": 35451362
 },
 {
  "name": "TsurugiSan",
  "position": 33511346
 },
 {
  "name": "Tsuruoka",
  "position": 384413950
 },
 {
  "name": "UchiuraWan",
  "position": 422514040
 },
 {
  "name": "Ueda",
  "position": 362413816
 },
 {
  "name": "Ujigunto",
  "position": 311512925
 },
 {
  "name": "UkeShima",
  "position": 28212914
 },
 {
  "name": "Uozu",
  "position": 364813724
 },
 {
  "name": "Urakawa",
  "position": 42914247
 },
 {
  "name": "Uwajima",
  "position": 331013235
 },
 {
  "name": "VotsuriShima",
  "position": 254512329
 },
 {
  "name": "Wakasa",
  "position": 352013424
 },
 {
  "name": "WakasaWan",
  "position": 354013530
 },
 {
  "name": "Wakayama",
  "position": 335013530
 },
 {
  "name": "Wakkanai",
  "position": 452814135
 },
 {
  "name": "Yaita",
  "position": 364813956
 },
 {
  "name": "Yamanashi",
  "position": 354013840
 },
 {
  "name": "Yame",
  "position": 331313035
 },
 {
  "name": "Yanagawa",
  "position": 33581327
 },
 {
  "name": "Yokote",
  "position": 392014030
 },
 {
  "name": "Yonago",
  "position": 352513319
 },
 {
  "name": "YoronJima",
  "position": 27212826
 },
 {
  "name": "Yubari",
  "position": 43414159
 },
 {
  "name": "Yubetsu",
  "position": 441314350
 },
 {
  "name": "Yuzawa",
  "position": 391014030
 }
]